<annotation>
	<folder>Mixed</folder>
	<filename>77cae2ca-8098-4c86-95db-351e3850dac5.jpg</filename>
	<path>C:\Users\MüllerHenning\PycharmProjects\logic-gate-simulator\images\mixed\77cae2ca-8098-4c86-95db-351e3850dac5.jpg</path>
	<source>
		<database>Unknown</database>
	</source>
	<size>
		<width>1440</width>
		<height>810</height>
		<depth>3</depth>
	</size>
	<segmented>0</segmented>
	<object>
		<name>switch_False</name>
		<pose>Unspecified</pose>
		<truncated>0</truncated>
		<difficult>0</difficult>
		<bndbox>
			<xmin>288</xmin>
			<ymin>361</ymin>
			<xmax>381</xmax>
			<ymax>427</ymax>
		</bndbox>
	</object>
	<object>
		<name>not</name>
		<pose>Unspecified</pose>
		<truncated>0</truncated>
		<difficult>0</difficult>
		<bndbox>
			<xmin>642</xmin>
			<ymin>295</ymin>
			<xmax>803</xmax>
			<ymax>352</ymax>
		</bndbox>
	</object>
	<object>
		<name>bulb</name>
		<pose>Unspecified</pose>
		<truncated>0</truncated>
		<difficult>0</difficult>
		<bndbox>
			<xmin>1036</xmin>
			<ymin>312</ymin>
			<xmax>1135</xmax>
			<ymax>378</ymax>
		</bndbox>
	</object>
</annotation>
