<annotation>
 	<folder>Mixed</folder>
 	<filename>adca65c8-f387-4429-bfe4-9b77d1572ec9.jpg</filename>
 	<path>C:\Users\MüllerHenning\PycharmProjects\logic-gate-simulator\images\mixed\adca65c8-f387-4429-bfe4-9b77d1572ec9.jpg</path>
 	<source>
 		<database>Unknown</database>
 	</source>
 	<size>
 		<width>1440</width>
 		<height>810</height>
 		<depth>3</depth>
 	</size>
 	<segmented>0</segmented>
 	<object>
 		<name>switch_True</name>
 		<pose>Unspecified</pose>
 		<truncated>0</truncated>
 		<difficult>0</difficult>
 		<bndbox>
 			<xmin>334</xmin>
 			<ymin>461</ymin>
 			<xmax>427</xmax>
 			<ymax>527</ymax>
 		</bndbox>
 	</object>
 	<object>
 		<name>bulb</name>
 		<pose>Unspecified</pose>
 		<truncated>0</truncated>
 		<difficult>0</difficult>
 		<bndbox>
 			<xmin>962</xmin>
 			<ymin>384</ymin>
 			<xmax>1061</xmax>
 			<ymax>450</ymax>
 		</bndbox>
 	</object>
 	<object>
 		<name>not</name>
 		<pose>Unspecified</pose>
 		<truncated>0</truncated>
 		<difficult>0</difficult>
 		<bndbox>
 			<xmin>638</xmin>
 			<ymin>464</ymin>
 			<xmax>799</xmax>
 			<ymax>521</ymax>
 		</bndbox>
 	</object>
 </annotation>
