<annotation>
	<folder>Mixed</folder>
	<filename>f525398c-c479-4734-9346-308354e2e98b.jpg</filename>
	<path>C:\Users\MüllerHenning\PycharmProjects\logic-gate-simulator\images\mixed\f525398c-c479-4734-9346-308354e2e98b.jpg</path>
	<source>
		<database>Unknown</database>
	</source>
	<size>
		<width>1440</width>
		<height>810</height>
		<depth>3</depth>
	</size>
	<segmented>0</segmented>
	<object>
		<name>switch_True</name>
		<pose>Unspecified</pose>
		<truncated>0</truncated>
		<difficult>0</difficult>
		<bndbox>
			<xmin>128</xmin>
			<ymin>172</ymin>
			<xmax>221</xmax>
			<ymax>238</ymax>
		</bndbox>
	</object>
	<object>
		<name>switch_True</name>
		<pose>Unspecified</pose>
		<truncated>0</truncated>
		<difficult>0</difficult>
		<bndbox>
			<xmin>89</xmin>
			<ymin>307</ymin>
			<xmax>182</xmax>
			<ymax>373</ymax>
		</bndbox>
	</object>
	<object>
		<name>switch_True</name>
		<pose>Unspecified</pose>
		<truncated>0</truncated>
		<difficult>0</difficult>
		<bndbox>
			<xmin>326</xmin>
			<ymin>507</ymin>
			<xmax>419</xmax>
			<ymax>573</ymax>
		</bndbox>
	</object>
	<object>
		<name>switch_True</name>
		<pose>Unspecified</pose>
		<truncated>0</truncated>
		<difficult>0</difficult>
		<bndbox>
			<xmin>322</xmin>
			<ymin>347</ymin>
			<xmax>415</xmax>
			<ymax>413</ymax>
		</bndbox>
	</object>
	<object>
		<name>and</name>
		<pose>Unspecified</pose>
		<truncated>0</truncated>
		<difficult>0</difficult>
		<bndbox>
			<xmin>670</xmin>
			<ymin>311</ymin>
			<xmax>831</xmax>
			<ymax>377</ymax>
		</bndbox>
	</object>
	<object>
		<name>or</name>
		<pose>Unspecified</pose>
		<truncated>0</truncated>
		<difficult>0</difficult>
		<bndbox>
			<xmin>915</xmin>
			<ymin>426</ymin>
			<xmax>1076</xmax>
			<ymax>492</ymax>
		</bndbox>
	</object>
	<object>
		<name>and</name>
		<pose>Unspecified</pose>
		<truncated>0</truncated>
		<difficult>0</difficult>
		<bndbox>
			<xmin>389</xmin>
			<ymin>203</ymin>
			<xmax>550</xmax>
			<ymax>269</ymax>
		</bndbox>
	</object>
	<object>
		<name>bulb</name>
		<pose>Unspecified</pose>
		<truncated>0</truncated>
		<difficult>0</difficult>
		<bndbox>
			<xmin>1248</xmin>
			<ymin>305</ymin>
			<xmax>1347</xmax>
			<ymax>371</ymax>
		</bndbox>
	</object>
</annotation>
